setup.py
pasteur/__init__.py
pasteur/__main__.py
pasteur/attribute.py
pasteur/cli.py
pasteur/dataset.py
pasteur/encode.py
pasteur/hierarchy.py
pasteur/metadata.py
pasteur/metric.py
pasteur/module.py
pasteur/synth.py
pasteur/table.py
pasteur/transform.py
pasteur/view.py
pasteur/extras/__init__.py
pasteur/extras/const.py
pasteur/extras/download.py
pasteur/extras/encoders.py
pasteur/extras/transformers.py
pasteur/extras/utils.py
pasteur/extras/datasets/__init__.py
pasteur/extras/datasets/sdgym.py
pasteur/extras/datasets/adult/__init__.py
pasteur/extras/datasets/mimic/__init__.py
pasteur/extras/datasets/texas/__init__.py
pasteur/extras/metrics/__init__.py
pasteur/extras/metrics/distr.py
pasteur/extras/metrics/visual.py
pasteur/extras/metrics/models/__init__.py
pasteur/extras/metrics/models/base.py
pasteur/extras/metrics/models/models.py
pasteur/extras/synth/__init__.py
pasteur/extras/synth/extern.py
pasteur/extras/synth/pgm/__init__.py
pasteur/extras/synth/pgm/aim.py
pasteur/extras/synth/pgm/common.py
pasteur/extras/synth/pgm/mst.py
pasteur/extras/synth/privbayes/__init__.py
pasteur/extras/synth/privbayes/implementation.py
pasteur/extras/views/__init__.py
pasteur/extras/views/adult/__init__.py
pasteur/extras/views/mimic/__init__.py
pasteur/extras/views/texas/__init__.py
pasteur/kedro/__init__.py
pasteur/kedro/cli.py
pasteur/kedro/dataset.py
pasteur/kedro/ipython.py
pasteur/kedro/utils.py
pasteur/kedro/hooks/__init__.py
pasteur/kedro/hooks/pasteur.py
pasteur/kedro/mlflow/__init__.py
pasteur/kedro/mlflow/base.py
pasteur/kedro/mlflow/config.py
pasteur/kedro/mlflow/hook.py
pasteur/kedro/mlflow/parent.py
pasteur/kedro/pipelines/__init__.py
pasteur/kedro/pipelines/dataset.py
pasteur/kedro/pipelines/main.py
pasteur/kedro/pipelines/meta.py
pasteur/kedro/pipelines/metrics.py
pasteur/kedro/pipelines/synth.py
pasteur/kedro/pipelines/transform.py
pasteur/kedro/pipelines/utils.py
pasteur/kedro/pipelines/views.py
pasteur/kedro/runner/__init__.py
pasteur/kedro/runner/common.py
pasteur-0.0.3.dist-info/LICENSE
pasteur-0.0.3.dist-info/METADATA
pasteur-0.0.3.dist-info/WHEEL
pasteur-0.0.3.dist-info/top_level.txt
pasteur-0.0.3.dist-info/RECORD
