Metadata-Version: 2.1
Name: pasteur
Version: 0.0.3
Summary: A system for reproducible and scalable data synthesis.
Author-email: Kapenekakis Antheas <antheas@cs.aau.dk>
Project-URL: Homepage, https://pasteur.dev
Project-URL: Bug Tracker, https://github.com/pasteur-dev/pasteur/issues
Classifier: Programming Language :: Python :: 3
Classifier: License :: OSI Approved :: Apache Software License
Classifier: Operating System :: OS Independent
Requires-Python: >=3.10
License-File: LICENSE
